jay_portal_gun/__init__.py
jay_portal_gun/__main__.py
jay_portal_gun/main.py
jay_portal_gun-0.2.0.dist-info/entry_points.txt
jay_portal_gun-0.2.0.dist-info/METADATA
jay_portal_gun-0.2.0.dist-info/WHEEL
jay_portal_gun-0.2.0.dist-info/RECORD
