Metadata-Version: 2.1
Name: jay-portal-gun
Version: 0.2.0
Summary: 
Author: Jmint
Author-email: jeffreymintah737@gmail.com
Requires-Python: >=3.11,<4.0
Classifier: Programming Language :: Python :: 3
Classifier: Programming Language :: Python :: 3.11
Classifier: Programming Language :: Python :: 3.12
Classifier: Programming Language :: Python :: 3.13
Requires-Dist: typer (>=0.15.1,<0.16.0)
